pykimo/__init__.py
pykimo-0.1.0.dist-info/METADATA
pykimo-0.1.0.dist-info/WHEEL
pykimo-0.1.0.dist-info/top_level.txt
pykimo-0.1.0.dist-info/RECORD
