Metadata-Version: 2.1
Name: pykimo
Version: 0.1.0
Summary: A lean AI chat agent library
Author: Mohamed Kimo
Author-email: your.email@example.com
